MANIFEST.in
setup.cfg
setup.py
gmmmc/__init__.py
gmmmc/gmm.py
gmmmc/monte_carlo.py
gmmmc/posterior.py
gmmmc.egg-info/PKG-INFO
gmmmc.egg-info/SOURCES.txt
gmmmc.egg-info/dependency_links.txt
gmmmc.egg-info/requires.txt
gmmmc.egg-info/top_level.txt
gmmmc/fastgmm/__init__.py
gmmmc/fastgmm/fast_likelihood.cpp
gmmmc/fastgmm/fast_likelihood.pyx
gmmmc/fastgmm/fast_likelihood_threaded.cpp
gmmmc/fastgmm/setup_fast_likelihood.py
gmmmc/priors/__init__.py
gmmmc/priors/prior.py
gmmmc/proposals/__init__.py
gmmmc/proposals/gaussian_proposals.py
gmmmc/proposals/proposals.py